django_orm_for_fastapi/__init__.py
django_orm_for_fastapi/consts.py
django_orm_for_fastapi/functions.py
django_orm_for_fastapi/test.py
django_orm_for_fastapi-0.1.2.dist-info/METADATA
django_orm_for_fastapi-0.1.2.dist-info/WHEEL
django_orm_for_fastapi-0.1.2.dist-info/RECORD
