Metadata-Version: 2.3
Name: django-orm-for-fastapi
Version: 0.1.2
Summary: 
Home-page: https://github.com/pkrefta/django-orm-for-fastapi
Author: Pawel Krefta
Author-email: pawel.krefta@gmail.com
Requires-Python: >=3.12
Classifier: Programming Language :: Python :: 3
Classifier: Programming Language :: Python :: 3.12
Classifier: Programming Language :: Python :: 3.13
Requires-Dist: django (>=5.2.4,<6.0.0)
Requires-Dist: fastapi (>=0.116.0,<0.117.0)
Project-URL: Issues, https://github.com/pkrefta/django-orm-for-fastapi/issues
Project-URL: Repository, https://github.com/pkrefta/django-orm-for-fastapi.git
